odoo/addons/mrp_bom_image/README.rst
odoo/addons/mrp_bom_image/__init__.py
odoo/addons/mrp_bom_image/__manifest__.py
odoo/addons/mrp_bom_image/i18n/it.po
odoo/addons/mrp_bom_image/i18n/mrp_bom_image.pot
odoo/addons/mrp_bom_image/i18n/pt_BR.po
odoo/addons/mrp_bom_image/models/__init__.py
odoo/addons/mrp_bom_image/models/mrp_bom.py
odoo/addons/mrp_bom_image/readme/CONTRIBUTORS.md
odoo/addons/mrp_bom_image/readme/DESCRIPTION.md
odoo/addons/mrp_bom_image/static/description/icon.png
odoo/addons/mrp_bom_image/static/description/index.html
odoo/addons/mrp_bom_image/static/description/mrp_bom_image.png
odoo/addons/mrp_bom_image/static/description/mrp_bom_image_kanban.png
odoo/addons/mrp_bom_image/views/view_mrp_bom.xml
odoo_addon_mrp_bom_image-18.0.1.0.0.3.dist-info/METADATA
odoo_addon_mrp_bom_image-18.0.1.0.0.3.dist-info/WHEEL
odoo_addon_mrp_bom_image-18.0.1.0.0.3.dist-info/top_level.txt
odoo_addon_mrp_bom_image-18.0.1.0.0.3.dist-info/RECORD
